npat/__init__.py
npat/dbmgr.py
npat/decay_chain.py
npat/irradiation.py
npat/isotope.py
npat/listfiles.py
npat/plotter.py
npat/reaction.py
npat/spectroscopy.py
npat-0.3.4.dist-info/LICENSE
npat-0.3.4.dist-info/METADATA
npat-0.3.4.dist-info/WHEEL
npat-0.3.4.dist-info/top_level.txt
npat-0.3.4.dist-info/RECORD
