Metadata-Version: 2.1
Name: npat
Version: 0.3.4
Summary: Nuclear Physics Analysis Tools (NPAT) is a library written in python to assist in analysis of the physics of nuclear reactions and spectroscopy.
Home-page: https://github.com/jtmorrell/npat
Author: Jonathan Morrell
Author-email: jmorrell@berkeley.edu
License: MIT
Platform: UNKNOWN
